python_use/__init__.py
python_use/__main__.py
python_use/default.toml
python_use/main.py
python_use/publish.py
python_use/saas.py
python_use/aipy/__init__.py
python_use/aipy/agent.py
python_use/aipy/i18n.py
python_use/aipy/interface.py
python_use/aipy/llm.py
python_use/aipy/runner.py
python_use/aipy/templates.py
python_use/aipy/utils.py
python_use-0.1.19.dist-info/METADATA
python_use-0.1.19.dist-info/WHEEL
python_use-0.1.19.dist-info/entry_points.txt
python_use-0.1.19.dist-info/licenses/LICENSE
python_use-0.1.19.dist-info/RECORD
