Metadata-Version: 2.4
Name: python-use
Version: 0.1.19
Summary: Python-Use: Python-Powered AI
License-File: LICENSE
Requires-Python: >=3.9
Requires-Dist: anthropic>=0.49.0
Requires-Dist: beautifulsoup4>=4.13.3
Requires-Dist: dynaconf>=3.2.10
Requires-Dist: google-api-python-client>=2.166.0
Requires-Dist: openai>=1.68.2
Requires-Dist: pandas>=2.2.3
Requires-Dist: plotpy>=2.7.3
Requires-Dist: prompt-toolkit>=3.0.50
Requires-Dist: pygments>=2.19.1
Requires-Dist: reportlab>=4.3.1
Requires-Dist: requests>=2.32.3
Requires-Dist: rich>=13.9.4
Requires-Dist: seaborn>=0.13.2
Requires-Dist: term-image>=0.7.2
